ducopy/__init__.py
ducopy/cli.py
ducopy/ducopy.py
ducopy/certs/api_cert.pem
ducopy/devicetree/box/genericbox.py
ducopy/rest/__init__.py
ducopy/rest/apikeygenerator.py
ducopy/rest/client.py
ducopy/rest/models.py
ducopy/rest/utils.py
ducopy-18.dist-info/licenses/LICENSE
ducopy-18.dist-info/METADATA
ducopy-18.dist-info/WHEEL
ducopy-18.dist-info/entry_points.txt
ducopy-18.dist-info/top_level.txt
ducopy-18.dist-info/RECORD
