Metadata-Version: 2.4
Name: ducopy
Version: 18
Summary: DucoPy: A Python library and CLI for full control over DucoBox ventilation units with a Connectivity Board. Retrieve system info, manage configurations, control nodes, and monitor logs easily from your Python environment or command line. 
Author-email: Thomas Phil <thomas@tphil.nl>
Classifier: Programming Language :: Python :: 3
Classifier: Programming Language :: Python :: 3.10
Classifier: Programming Language :: Python :: 3.11
Classifier: License :: OSI Approved :: MIT License
Classifier: Operating System :: OS Independent
Requires-Python: >=3.10
License-File: LICENSE
Requires-Dist: pydantic<3,>=1.10.17
Requires-Dist: requests<3,>=2.32.3
Requires-Dist: loguru<1,>=0.7.2
Requires-Dist: typer<1,>=0.12.5
Requires-Dist: rich<14,>=13.9.4
Provides-Extra: dev
Requires-Dist: pytest<8,>=7.4.0; extra == "dev"
Requires-Dist: requests-mock<2,>=1.11.0; extra == "dev"
Requires-Dist: pytest-cov<5,>=4.1.0; extra == "dev"
Requires-Dist: flake8<7,>=6.1.0; extra == "dev"
Requires-Dist: black<24,>=23.9.1; extra == "dev"
Requires-Dist: mypy<2,>=1.6.0; extra == "dev"
Requires-Dist: Flask<3,>=2.3.3; extra == "dev"
Requires-Dist: ruff<1,>=0.7.2; extra == "dev"
Requires-Dist: pre-commit<5,>=4.0.1; extra == "dev"
Requires-Dist: pytest>=6.0; extra == "dev"
Provides-Extra: build
Requires-Dist: build; extra == "build"
Requires-Dist: twine; extra == "build"
Requires-Dist: pytest<8,>=7.4.0; extra == "build"
Requires-Dist: requests-mock<2,>=1.11.0; extra == "build"
Requires-Dist: pytest-cov<5,>=4.1.0; extra == "build"
Requires-Dist: flake8<7,>=6.1.0; extra == "build"
Requires-Dist: black<24,>=23.9.1; extra == "build"
Requires-Dist: mypy<2,>=1.6.0; extra == "build"
Requires-Dist: Flask<3,>=2.3.3; extra == "build"
Requires-Dist: ruff<1,>=0.7.2; extra == "build"
Requires-Dist: pre-commit<5,>=4.0.1; extra == "build"
Requires-Dist: pytest>=6.0; extra == "build"
Dynamic: license-file
